signal_mcp_client/__init__.py
signal_mcp_client/_version.py
signal_mcp_client/build_in_tools.py
signal_mcp_client/history.py
signal_mcp_client/main.py
signal_mcp_client/mcp_client.py
signal_mcp_client-0.1.8.dist-info/licenses/LICENSE
signal_mcp_client-0.1.8.dist-info/METADATA
signal_mcp_client-0.1.8.dist-info/WHEEL
signal_mcp_client-0.1.8.dist-info/entry_points.txt
signal_mcp_client-0.1.8.dist-info/top_level.txt
signal_mcp_client-0.1.8.dist-info/RECORD
