Metadata-Version: 2.4
Name: signal-mcp-client
Version: 0.1.8
Summary: An MCP client that uses signal for sending and receiving texts.
Author-email: Piet Brömmel <piet.broemmel@gmail.com>
License-Expression: MIT
Project-URL: Homepage, https://github.com/piebro/signal-mcp-client
Project-URL: Bug Tracker, https://github.com/piebro/signal-mcp-client/issues
Keywords: mcp,client,signal,bot,ai
Classifier: Development Status :: 4 - Beta
Classifier: Intended Audience :: Developers
Classifier: Programming Language :: Python :: 3
Classifier: Programming Language :: Python :: 3.10
Requires-Python: >=3.10
License-File: LICENSE
Requires-Dist: mcp>=1.3.0
Requires-Dist: python-dotenv>=1.0.1
Requires-Dist: websockets
Requires-Dist: requests
Requires-Dist: litellm==1.67.2
Requires-Dist: ruff
Requires-Dist: fal-client
Dynamic: license-file
